[
 {
  "creation": "2026-05-10 12:00:00.000000",
  "custom_format": 1,
  "default_print_language": null,
  "disabled": 0,
  "doc_type": "Case",
  "docstatus": 0,
  "doctype": "Print Format",
  "font": "Default",
  "idx": 0,
  "line_breaks": 0,
  "modified": "2026-05-10 12:00:00.000000",
  "modified_by": "Administrator",
  "module": "Lawfirm Addons",
  "name": "Case Sessions Print",
  "owner": "Administrator",
  "print_format_builder": 0,
  "print_format_type": "Jinja",
  "raw_printing": 0,
  "show_section_headings": 0,
  "standard": "No",
  "html": "<div style=\"direction:rtl;text-align:center;margin-bottom:14px;\">\n  <h2 style=\"font-size:22px;font-weight:700;margin:0 0 10px 0;\">تقرير جدول الجلسات</h2>\n  {% set first_row = doc.case_sessions[0] if doc.case_sessions else None %}\n  <p style=\"font-size:16px;line-height:2;margin:0;\">\n    <span style=\"font-weight:700;\">ملف القضية:</span> <span style=\"font-weight:600;\">{{ doc.name }}</span>\n    &nbsp;&nbsp; <span style=\"font-weight:700;\">اسم العميل:</span> <span style=\"font-weight:600;\">{{ doc.customer_name or \"\" }}</span>\n    {% if first_row %}\n    &nbsp;&nbsp; <span style=\"font-weight:700;\">صفة العميل:</span> <span style=\"font-weight:600;\">{{ first_row.client_capacity or \"\" }}</span>\n    &nbsp;&nbsp; <span style=\"font-weight:700;\">الخصم:</span> <span style=\"font-weight:600;\">{{ first_row.opponent or \"\" }}</span>\n    &nbsp;&nbsp; <span style=\"font-weight:700;\">صفة الخصم:</span> <span style=\"font-weight:600;\">{{ first_row.opponent_capacity or \"\" }}</span>\n    {% endif %}\n  </p>\n</div>\n<table class=\"table table-bordered\" style=\"width:100%;direction:rtl;font-size:11px;\">\n  <thead>\n    <tr>\n      <th>تاريخ الجلسة الأولى</th>\n      <th>المحكمة</th>\n      <th>الدرجة</th>\n      <th>المسلسل</th>\n      <th>الدائرة</th>\n      <th>موضوع القضية</th>\n      <th>مكان الجلسة</th>\n      <th>مكان الحضور</th>\n      <th>صفة العميل</th>\n      <th>الخصم</th>\n      <th>صفة الخصم</th>\n      <th>القرار السابق</th>\n      <th style=\"min-width:220px;\">قرار الجلسة</th>\n      <th>الطلبات</th>\n      <th>تاريخ الجلسة القادمة</th>\n    </tr>\n  </thead>\n  <tbody>\n    {% for row in doc.case_sessions %}\n    <tr>\n      <td style=\"font-weight:600;\">{{ frappe.utils.formatdate(row.business_on_date, \"dd-mm-yyyy\") if row.business_on_date else \"\" }}</td>\n      <td>{{ row.court or \"\" }}</td>\n      <td>{{ row.litigation_degree or \"\" }}</td>\n      <td>{{ row.registration_no or \"\" }}</td>\n      <td>{{ row.chamber or \"\" }}</td>\n      <td>{{ row.case_subject or \"\" }}</td>\n      <td>{{ row.case_location or \"\" }}</td>\n      <td>{{ row.attendance_location or \"\" }}</td>\n      <td>{{ row.client_capacity or \"\" }}</td>\n      <td>{{ row.opponent or \"\" }}</td>\n      <td>{{ row.opponent_capacity or \"\" }}</td>\n      <td>{{ row.previous_decision or \"\" }}</td>\n      <td style=\"font-size:12px;\">{{ row.decision or \"\" }}</td>\n      <td>{{ row.defense_summary or \"\" }}</td>\n      <td style=\"font-weight:600;\">{{ frappe.utils.formatdate(row.next_date, \"dd-mm-yyyy\") if row.next_date else \"\" }}</td>\n    </tr>\n    {% endfor %}\n  </tbody>\n</table>"
 },
 {
  "creation": "2026-05-10 12:00:00.000000",
  "custom_format": 1,
  "default_print_language": null,
  "disabled": 0,
  "doc_type": "Case",
  "docstatus": 0,
  "doctype": "Print Format",
  "font": "Default",
  "idx": 0,
  "line_breaks": 0,
  "modified": "2026-05-10 12:00:00.000000",
  "modified_by": "Administrator",
  "module": "Lawfirm Addons",
  "name": "Case History Print",
  "owner": "Administrator",
  "print_format_builder": 0,
  "print_format_type": "Jinja",
  "raw_printing": 0,
  "show_section_headings": 0,
  "standard": "No",
  "html": "<h2 style=\"text-align:center;font-size:22px;font-weight:700;\">تقرير جدول الجلسات (السجل)</h2>\n<div style=\"direction:rtl;text-align:center;margin-bottom:12px;font-size:16px;line-height:2;\">\n  {% set first_row = doc.case_history[0] if doc.case_history else None %}\n  <span style=\"font-weight:700;\">ملف القضية:</span> <span style=\"font-weight:600;\">{{ doc.name }}</span>\n  &nbsp;&nbsp; <span style=\"font-weight:700;\">اسم العميل:</span> <span style=\"font-weight:600;\">{{ doc.customer_name or \"\" }}</span>\n  {% if first_row %}\n  &nbsp;&nbsp; <span style=\"font-weight:700;\">صفة العميل:</span> <span style=\"font-weight:600;\">{{ first_row.client_capacity or \"\" }}</span>\n  &nbsp;&nbsp; <span style=\"font-weight:700;\">الخصم:</span> <span style=\"font-weight:600;\">{{ first_row.opponent or \"\" }}</span>\n  &nbsp;&nbsp; <span style=\"font-weight:700;\">صفة الخصم:</span> <span style=\"font-weight:600;\">{{ first_row.opponent_capacity or \"\" }}</span>\n  {% endif %}\n</div>\n<table class=\"table table-bordered\" style=\"width:100%;direction:rtl;font-size:11px;\">\n  <thead>\n    <tr>\n      <th>تاريخ الجلسة الأولى</th>\n      <th>المحكمة</th>\n      <th>الدرجة</th>\n      <th>المسلسل</th>\n      <th>الدائرة</th>\n      <th>موضوع القضية</th>\n      <th>مكان الجلسة</th>\n      <th>مكان الحضور</th>\n      <th>صفة العميل</th>\n      <th>الخصم</th>\n      <th>صفة الخصم</th>\n      <th>القرار السابق</th>\n      <th style=\"min-width:220px;\">قرار الجلسة</th>\n      <th>الطلبات</th>\n    </tr>\n  </thead>\n  <tbody>\n    {% for row in doc.case_history %}\n    <tr>\n      <td style=\"font-weight:600;\">{{ frappe.utils.formatdate(row.business_on_date, \"dd-mm-yyyy\") if row.business_on_date else \"\" }}</td>\n      <td>{{ row.court or \"\" }}</td>\n      <td>{{ row.litigation_degree or \"\" }}</td>\n      <td>{{ row.registration_no or \"\" }}</td>\n      <td>{{ row.chamber or \"\" }}</td>\n      <td>{{ row.case_subject or \"\" }}</td>\n      <td>{{ row.case_location or \"\" }}</td>\n      <td>{{ row.attendance_location or \"\" }}</td>\n      <td>{{ row.client_capacity or \"\" }}</td>\n      <td>{{ row.opponent or \"\" }}</td>\n      <td>{{ row.opponent_capacity or \"\" }}</td>\n      <td>{{ row.previous_decision or \"\" }}</td>\n      <td style=\"font-size:12px;\">{{ row.decision or \"\" }}</td>\n      <td>{{ row.defense_summary or \"\" }}</td>\n    </tr>\n    {% endfor %}\n  </tbody>\n</table>"
 },
 {
  "creation": "2026-05-10 12:00:00.000000",
  "custom_format": 1,
  "default_print_language": null,
  "disabled": 0,
  "doc_type": "Case",
  "docstatus": 0,
  "doctype": "Print Format",
  "font": "Default",
  "idx": 0,
  "line_breaks": 0,
  "modified": "2026-05-10 12:00:00.000000",
  "modified_by": "Administrator",
  "module": "Lawfirm Addons",
  "name": "Case Sessions Report Print",
  "owner": "Administrator",
  "print_format_builder": 0,
  "print_format_type": "Jinja",
  "raw_printing": 0,
  "show_section_headings": 0,
  "standard": "No",
  "html": "<div style=\"direction:rtl;text-align:center;margin-bottom:14px;\">\n  <h2 style=\"font-size:22px;font-weight:700;margin:0 0 10px 0;\">تقرير الجلسات — طباعة</h2>\n  {% set first_row = doc.case_sessions[0] if doc.case_sessions else None %}\n  <p style=\"font-size:16px;line-height:2;margin:0;\">\n    <span style=\"font-weight:700;\">ملف القضية:</span> <span style=\"font-weight:600;\">{{ doc.name }}</span>\n    &nbsp;&nbsp; <span style=\"font-weight:700;\">اسم العميل:</span> <span style=\"font-weight:600;\">{{ doc.customer_name or \"\" }}</span>\n    {% if first_row %}\n    &nbsp;&nbsp; <span style=\"font-weight:700;\">صفة العميل:</span> <span style=\"font-weight:600;\">{{ first_row.client_capacity or \"\" }}</span>\n    &nbsp;&nbsp; <span style=\"font-weight:700;\">الخصم:</span> <span style=\"font-weight:600;\">{{ first_row.opponent or \"\" }}</span>\n    &nbsp;&nbsp; <span style=\"font-weight:700;\">صفة الخصم:</span> <span style=\"font-weight:600;\">{{ first_row.opponent_capacity or \"\" }}</span>\n    {% endif %}\n  </p>\n</div>\n<table class=\"table table-bordered\" style=\"width:100%;direction:rtl;font-size:11px;\">\n  <thead>\n    <tr>\n      <th>تاريخ الجلسة الأولى</th>\n      <th>المحكمة</th>\n      <th>الدرجة</th>\n      <th>المسلسل</th>\n      <th>الدائرة</th>\n      <th>موضوع القضية</th>\n      <th>مكان الجلسة</th>\n      <th>مكان الحضور</th>\n      <th>صفة العميل</th>\n      <th>الخصم</th>\n      <th>صفة الخصم</th>\n      <th>القرار السابق</th>\n      <th style=\"min-width:220px;\">قرار الجلسة</th>\n      <th>الطلبات</th>\n      <th>تاريخ الجلسة القادمة</th>\n    </tr>\n  </thead>\n  <tbody>\n    {% for row in doc.case_sessions %}\n    <tr>\n      <td style=\"font-weight:600;\">{{ frappe.utils.formatdate(row.business_on_date, \"dd-mm-yyyy\") if row.business_on_date else \"\" }}</td>\n      <td>{{ row.court or \"\" }}</td>\n      <td>{{ row.litigation_degree or \"\" }}</td>\n      <td>{{ row.registration_no or \"\" }}</td>\n      <td>{{ row.chamber or \"\" }}</td>\n      <td>{{ row.case_subject or \"\" }}</td>\n      <td>{{ row.case_location or \"\" }}</td>\n      <td>{{ row.attendance_location or \"\" }}</td>\n      <td>{{ row.client_capacity or \"\" }}</td>\n      <td>{{ row.opponent or \"\" }}</td>\n      <td>{{ row.opponent_capacity or \"\" }}</td>\n      <td>{{ row.previous_decision or \"\" }}</td>\n      <td style=\"font-size:12px;\">{{ row.decision or \"\" }}</td>\n      <td>{{ row.defense_summary or \"\" }}</td>\n      <td style=\"font-weight:600;\">{{ frappe.utils.formatdate(row.next_date, \"dd-mm-yyyy\") if row.next_date else \"\" }}</td>\n    </tr>\n    {% endfor %}\n  </tbody>\n</table>"
 },
 {
  "creation": "2026-05-10 12:00:00.000000",
  "custom_format": 1,
  "default_print_language": null,
  "disabled": 0,
  "doc_type": "Case",
  "docstatus": 0,
  "doctype": "Print Format",
  "font": "Default",
  "idx": 0,
  "line_breaks": 0,
  "modified": "2026-05-10 12:00:00.000000",
  "modified_by": "Administrator",
  "module": "Lawfirm Addons",
  "name": "Case History Report Print",
  "owner": "Administrator",
  "print_format_builder": 0,
  "print_format_type": "Jinja",
  "raw_printing": 0,
  "show_section_headings": 0,
  "standard": "No",
  "html": "<h2 style=\"text-align:center;font-size:22px;font-weight:700;\">تقرير السجل — طباعة</h2>\n<div style=\"direction:rtl;text-align:center;margin-bottom:12px;font-size:16px;line-height:2;\">\n  {% set first_row = doc.case_history[0] if doc.case_history else None %}\n  <span style=\"font-weight:700;\">ملف القضية:</span> <span style=\"font-weight:600;\">{{ doc.name }}</span>\n  &nbsp;&nbsp; <span style=\"font-weight:700;\">اسم العميل:</span> <span style=\"font-weight:600;\">{{ doc.customer_name or \"\" }}</span>\n  {% if first_row %}\n  &nbsp;&nbsp; <span style=\"font-weight:700;\">صفة العميل:</span> <span style=\"font-weight:600;\">{{ first_row.client_capacity or \"\" }}</span>\n  &nbsp;&nbsp; <span style=\"font-weight:700;\">الخصم:</span> <span style=\"font-weight:600;\">{{ first_row.opponent or \"\" }}</span>\n  &nbsp;&nbsp; <span style=\"font-weight:700;\">صفة الخصم:</span> <span style=\"font-weight:600;\">{{ first_row.opponent_capacity or \"\" }}</span>\n  {% endif %}\n</div>\n<table class=\"table table-bordered\" style=\"width:100%;direction:rtl;font-size:11px;\">\n  <thead>\n    <tr>\n      <th>تاريخ الجلسة الأولى</th>\n      <th>المحكمة</th>\n      <th>الدرجة</th>\n      <th>المسلسل</th>\n      <th>الدائرة</th>\n      <th>موضوع القضية</th>\n      <th>مكان الجلسة</th>\n      <th>مكان الحضور</th>\n      <th>صفة العميل</th>\n      <th>الخصم</th>\n      <th>صفة الخصم</th>\n      <th>القرار السابق</th>\n      <th style=\"min-width:220px;\">قرار الجلسة</th>\n      <th>الطلبات</th>\n    </tr>\n  </thead>\n  <tbody>\n    {% for row in doc.case_history %}\n    <tr>\n      <td style=\"font-weight:600;\">{{ frappe.utils.formatdate(row.business_on_date, \"dd-mm-yyyy\") if row.business_on_date else \"\" }}</td>\n      <td>{{ row.court or \"\" }}</td>\n      <td>{{ row.litigation_degree or \"\" }}</td>\n      <td>{{ row.registration_no or \"\" }}</td>\n      <td>{{ row.chamber or \"\" }}</td>\n      <td>{{ row.case_subject or \"\" }}</td>\n      <td>{{ row.case_location or \"\" }}</td>\n      <td>{{ row.attendance_location or \"\" }}</td>\n      <td>{{ row.client_capacity or \"\" }}</td>\n      <td>{{ row.opponent or \"\" }}</td>\n      <td>{{ row.opponent_capacity or \"\" }}</td>\n      <td>{{ row.previous_decision or \"\" }}</td>\n      <td style=\"font-size:12px;\">{{ row.decision or \"\" }}</td>\n      <td>{{ row.defense_summary or \"\" }}</td>\n    </tr>\n    {% endfor %}\n  </tbody>\n</table>"
 },
 {
  "creation": "2026-05-10 12:00:00.000000",
  "custom_format": 1,
  "default_print_language": null,
  "disabled": 0,
  "doc_type": "Sales Invoice",
  "docstatus": 0,
  "doctype": "Print Format",
  "font": "Default",
  "idx": 0,
  "line_breaks": 0,
  "modified": "2026-05-10 12:00:00.000000",
  "modified_by": "Administrator",
  "module": "Lawfirm Addons",
  "name": "Sales Invoice - فاتورة رسوم دعوى",
  "owner": "Administrator",
  "print_format_builder": 0,
  "print_format_type": "Jinja",
  "raw_printing": 0,
  "show_section_headings": 0,
  "standard": "No",
  "html": "<div dir=\"rtl\" style=\"font-family:Tahoma,Arial,sans-serif;padding:12px;\">\n  <div style=\"display:flex;justify-content:space-between;align-items:flex-start;margin-bottom:16px;\">\n    <div><h2 style=\"margin:0;\">فاتورة رسوم دعوى</h2></div>\n    <div style=\"text-align:left;\">{% if doc.custom_invoice_type %}<strong>نوع الفاتورة:</strong> {{ doc.custom_invoice_type }}{% endif %}</div>\n  </div>\n  <p><strong>العميل:</strong> {{ doc.customer_name or doc.customer }}</p>\n  <p><strong>رقم الفاتورة:</strong> {{ doc.name }} &nbsp; <strong>التاريخ:</strong> {{ frappe.utils.formatdate(doc.posting_date) }}</p>\n  <table class=\"table table-bordered\" style=\"width:100%;margin-top:12px;\">\n    <thead><tr><th>البند</th><th>الوصف</th><th>الكمية</th><th>السعر</th><th>المبلغ</th></tr></thead>\n    <tbody>\n    {% for it in doc.items %}\n      <tr><td>{{ it.item_code }}</td><td>{{ it.description or \"\" }}</td><td>{{ it.qty }}</td><td>{{ it.rate }}</td><td>{{ it.amount }}</td></tr>\n    {% endfor %}\n    </tbody>\n  </table>\n  <p style=\"margin-top:12px;\"><strong>الإجمالي:</strong> {{ doc.grand_total }} {{ doc.currency }}</p>\n</div>"
 },
 {
  "creation": "2026-05-10 12:00:00.000000",
  "custom_format": 1,
  "default_print_language": null,
  "disabled": 0,
  "doc_type": "Sales Invoice",
  "docstatus": 0,
  "doctype": "Print Format",
  "font": "Default",
  "idx": 0,
  "line_breaks": 0,
  "modified": "2026-05-10 12:00:00.000000",
  "modified_by": "Administrator",
  "module": "Lawfirm Addons",
  "name": "Sales Invoice - فاتورة اتعاب",
  "owner": "Administrator",
  "print_format_builder": 0,
  "print_format_type": "Jinja",
  "raw_printing": 0,
  "show_section_headings": 0,
  "standard": "No",
  "html": "<div dir=\"rtl\" style=\"font-family:Tahoma,Arial,sans-serif;padding:12px;\">\n  <div style=\"display:flex;justify-content:space-between;align-items:flex-start;margin-bottom:16px;\">\n    <div><h2 style=\"margin:0;\">فاتورة اتعاب</h2></div>\n    <div style=\"text-align:left;\">{% if doc.custom_invoice_type %}<strong>نوع الفاتورة:</strong> {{ doc.custom_invoice_type }}{% endif %}</div>\n  </div>\n  <p><strong>العميل:</strong> {{ doc.customer_name or doc.customer }}</p>\n  <p><strong>رقم الفاتورة:</strong> {{ doc.name }} &nbsp; <strong>التاريخ:</strong> {{ frappe.utils.formatdate(doc.posting_date) }}</p>\n  <table class=\"table table-bordered\" style=\"width:100%;margin-top:12px;\">\n    <thead><tr><th>البند</th><th>الوصف</th><th>الكمية</th><th>السعر</th><th>المبلغ</th></tr></thead>\n    <tbody>\n    {% for it in doc.items %}\n      <tr><td>{{ it.item_code }}</td><td>{{ it.description or \"\" }}</td><td>{{ it.qty }}</td><td>{{ it.rate }}</td><td>{{ it.amount }}</td></tr>\n    {% endfor %}\n    </tbody>\n  </table>\n  <p style=\"margin-top:12px;\"><strong>الإجمالي:</strong> {{ doc.grand_total }} {{ doc.currency }}</p>\n</div>"
 },
 {
  "creation": "2026-05-10 12:00:00.000000",
  "custom_format": 1,
  "default_print_language": null,
  "disabled": 0,
  "doc_type": "Payment Entry",
  "docstatus": 0,
  "doctype": "Print Format",
  "font": "Default",
  "idx": 0,
  "line_breaks": 0,
  "modified": "2026-05-10 12:00:00.000000",
  "modified_by": "Administrator",
  "module": "Lawfirm Addons",
  "name": "Payment Entry - استلام مبلغ عن فاتورة رسوم دعوى",
  "owner": "Administrator",
  "print_format_builder": 0,
  "print_format_type": "Jinja",
  "raw_printing": 0,
  "show_section_headings": 0,
  "standard": "No",
  "html": "<div dir=\"rtl\" style=\"font-family:Tahoma,Arial,sans-serif;padding:12px;\">\n  <h2>استلام مبلغ عن فاتورة رسوم دعوى</h2>\n  <p><strong>المرجع:</strong> {{ doc.name }}</p>\n  <p><strong>التاريخ:</strong> {{ frappe.utils.formatdate(doc.posting_date) }}</p>\n  <p><strong>نوع الدفع:</strong> {{ doc.payment_type }}</p>\n  <p><strong>الطرف:</strong> {{ doc.party_type }} — {{ doc.party }}</p>\n  <p><strong>المبلغ المستلم:</strong> {{ doc.paid_amount }} {{ doc.paid_from_account_currency or \"\" }}</p>\n  {% if doc.references %}\n  <table class=\"table table-bordered\" style=\"width:100%;margin-top:8px;\"><thead><tr><th>المرجع</th><th>المبلغ المخصص</th></tr></thead><tbody>\n  {% for r in doc.references %}\n    <tr><td>{{ r.reference_doctype }} {{ r.reference_name }}</td><td>{{ r.allocated_amount }}</td></tr>\n  {% endfor %}\n  </tbody></table>\n  {% endif %}\n</div>"
 },
 {
  "creation": "2026-05-10 12:00:00.000000",
  "custom_format": 1,
  "default_print_language": null,
  "disabled": 0,
  "doc_type": "Payment Entry",
  "docstatus": 0,
  "doctype": "Print Format",
  "font": "Default",
  "idx": 0,
  "line_breaks": 0,
  "modified": "2026-05-10 12:00:00.000000",
  "modified_by": "Administrator",
  "module": "Lawfirm Addons",
  "name": "Payment Entry - استلام مبلغ عن فاتورة اتعاب",
  "owner": "Administrator",
  "print_format_builder": 0,
  "print_format_type": "Jinja",
  "raw_printing": 0,
  "show_section_headings": 0,
  "standard": "No",
  "html": "<div dir=\"rtl\" style=\"font-family:Tahoma,Arial,sans-serif;padding:12px;\">\n  <h2>استلام مبلغ عن فاتورة اتعاب</h2>\n  <p><strong>المرجع:</strong> {{ doc.name }}</p>\n  <p><strong>التاريخ:</strong> {{ frappe.utils.formatdate(doc.posting_date) }}</p>\n  <p><strong>نوع الدفع:</strong> {{ doc.payment_type }}</p>\n  <p><strong>الطرف:</strong> {{ doc.party_type }} — {{ doc.party }}</p>\n  <p><strong>المبلغ المستلم:</strong> {{ doc.paid_amount }} {{ doc.paid_from_account_currency or \"\" }}</p>\n  {% if doc.references %}\n  <table class=\"table table-bordered\" style=\"width:100%;margin-top:8px;\"><thead><tr><th>المرجع</th><th>المبلغ المخصص</th></tr></thead><tbody>\n  {% for r in doc.references %}\n    <tr><td>{{ r.reference_doctype }} {{ r.reference_name }}</td><td>{{ r.allocated_amount }}</td></tr>\n  {% endfor %}\n  </tbody></table>\n  {% endif %}\n</div>"
 }
]